datadock/__init__.py
datadock/core/__init__.py
datadock/core/_rich_.py
datadock/core/_table_.py
datadock/core/_xml_.py
datadock/core/extract_text.py
datadock/core/filing.py
datadock/core/filters.py
datadock/factory/__init__.py
datadock/factory/formfactory.py
datadock/factory/patterns.py
datadock/factory/requestfactory.py
datadock/factory/scrape_financials.py
datadock/form_controller/__init__.py
datadock/form_controller/_control_10k_.py
datadock/form_controller/_control_13fhr_.py
datadock/form_controller/_control_13fnt_.py
datadock/form_controller/_control_8k_.py
datadock/form_controller/_control_d_.py
datadock/form_controller/_control_sc13d_.py
datadock/form_controller/_control_sc13g_.py
datadock/form_controller/handler.py
datadock/metadata/__init__.py
datadock/metadata/__version__.py
datadock/src/__init__.py
datadock/src/_base_request.py
datadock/src/_constants.py
datadock/src/_errors.py
datadock/src/config.py
datadock/src/data_class.py
datadock/src/generators.py
datadock/src/logger.py
datadock/src/models.py
datadock/src/utils.py
datadock/utils/__init__.py
datadock/utils/_compact_.py
datadock-2.0.11.dist-info/LICENSE
datadock-2.0.11.dist-info/METADATA
datadock-2.0.11.dist-info/WHEEL
datadock-2.0.11.dist-info/RECORD
