Metadata-Version: 2.3
Name: datadock
Version: 2.0.11
Summary: DataDock python library to access SEC edgar fillings.
License: MIT
Keywords: datadockpy,datadockAI,python,SEC
Author: Peter Mbachu
Author-email: peter.mbachu@datadock.ai
Requires-Python: >=3.10,<4.0
Classifier: Development Status :: 5 - Production/Stable
Classifier: Intended Audience :: Developers
Classifier: License :: OSI Approved :: MIT License
Classifier: Natural Language :: English
Classifier: Operating System :: OS Independent
Classifier: Programming Language :: Python :: 3
Classifier: Programming Language :: Python :: 3.10
Classifier: Programming Language :: Python :: 3.11
Classifier: Programming Language :: Python :: 3.12
Classifier: Programming Language :: Python :: 3.13
Classifier: Topic :: Software Development :: Libraries :: Python Modules
Requires-Dist: beautifulsoup4 (>=4.12,<5.0)
Requires-Dist: colorama (>=0.4,<0.5)
Requires-Dist: fastcore (>=1.7,<2.0)
Requires-Dist: humanize (>=4.11,<5.0)
Requires-Dist: lxml (>=5.3,<6.0)
Requires-Dist: pandas (>=2.2,<3.0)
Requires-Dist: pyarrow (>=17.0,<18.0)
Requires-Dist: pydantic (>=2.9,<3.0)
Requires-Dist: python-decouple (>=3.8,<4.0)
Requires-Dist: requests (>=2.32,<3.0)
Requires-Dist: rich (>=13.8,<14.0)
